woostream/__main__.py
woostream-0.1.7.dist-info/METADATA
woostream-0.1.7.dist-info/WHEEL
woostream-0.1.7.dist-info/RECORD
