Metadata-Version: 2.1
Name: woostream
Version: 0.1.7
Summary: Listen to fills & position updates on Woo X
License: MIT
Author: waterquarks
Author-email: waterquarks@gmail.com
Requires-Python: >=3.10,<4.0
Classifier: License :: OSI Approved :: MIT License
Classifier: Programming Language :: Python :: 3
Classifier: Programming Language :: Python :: 3.10
Classifier: Programming Language :: Python :: 3.11
Requires-Dist: aiohttp (>=3.8.4,<4.0.0)
Requires-Dist: aiostream (>=0.4.5,<0.5.0)
Requires-Dist: python-telegram-bot (>=20.2,<21.0)
Requires-Dist: websockets (>=11.0.2,<12.0.0)
